LICENSE
caltrain.py
setup.cfg
setup.py
caltrain.egg-info/PKG-INFO
caltrain.egg-info/SOURCES.txt
caltrain.egg-info/dependency_links.txt
caltrain.egg-info/entry_points.txt
caltrain.egg-info/requires.txt
caltrain.egg-info/top_level.txt
caltrain.egg-info/zip-safe