Metadata-Version: 1.0
Name: caltrain
Version: 0.6
Summary: GUI and library for Caltrain schedules
Home-page: http://www.heikkitoivonen.net/caltrain
Author: Heikki Toivonen
Author-email: My first name at heikkitoivonen.net
License: The MIT License
Platform: any
Classifier: Development Status :: 4 - Beta
Classifier: Intended Audience :: Developers
Classifier: Intended Audience :: End Users/Desktop
Classifier: License :: OSI Approved :: MIT License
Classifier: Operating System :: OS Independent
Classifier: Programming Language :: Python
Classifier: Topic :: Software Development :: Libraries :: Python Modules
